reign_airflow_utils/__init__.py
reign_airflow_utils/secret_backends.py
reign_airflow_utils/hooks/__init__.py
reign_airflow_utils/hooks/oracle_hook.py
reign_airflow_utils/operators/__init__.py
reign_airflow_utils/operators/oracle/__init__.py
reign_airflow_utils/operators/oracle/dump_expert.py
reign_airflow_utils-0.1.4.dist-info/LICENSE
reign_airflow_utils-0.1.4.dist-info/METADATA
reign_airflow_utils-0.1.4.dist-info/WHEEL
reign_airflow_utils-0.1.4.dist-info/top_level.txt
reign_airflow_utils-0.1.4.dist-info/RECORD
