Metadata-Version: 2.1
Name: reign-airflow-utils
Version: 0.1.4
Summary: A package of airflow utils
License-File: LICENSE
Requires-Dist: apache-airflow[oracle] (>=2.2.0)
